slactorbot
