Metadata-Version: 1.1
Name: slactorbot
Version: 0.0.5
Summary: A Python Slack Bot with hot patch!
Home-page: https://github.com/dataloop/slactorbot
Author: Steven Acreman
Author-email: steven.acreman@dataloop.io
License: MIT
Download-URL: https://github.com/dataloop/slactorbot/tarball/v0.0.5
Keywords: slack bot
Platform: any
Classifier: Intended Audience :: Developers
Classifier: Intended Audience :: System Administrators
